[
    {
        "bookId": 1,
        "bookName": "The Da Vinci Code",
        "author": "Dan Brown",
        "image": "https://i.postimg.cc/pdPKV5Tm/9780307277671.jpg",
        "review": "An enthralling mystery that keeps you guessing until the very end.",
        "totalPages": 454,
        "rating": 4.3,
        "category": "Mystery",
        "tags": ["Suspense", "Conspiracy"],
        "publisher": "Doubleday",
        "yearOfPublishing": 2003,
        "type": "bookCard"
    },
    {
        "bookId": 2,
        "bookName": "The Hate U Give",
        "author": "Suzanne Collins",
        "image": "https://i.postimg.cc/vZcpqDM6/32075671.jpg",
        "review": "A gripping dystopian tale filled with action and heart.",
        "totalPages": 374,
        "rating": 4.5,
        "category": "Science Fiction",
        "tags": ["Dystopian", "Adventure"],
        "publisher": "Scholastic Press",
        "yearOfPublishing": 2008,
        "type": "bookCard"
    },
    {
        "bookId": 3,
        "bookName": "The Catcher in the",
        "author": "J.D. Salinger",
        "image": "https://i.postimg.cc/63g0Q6gF/5107.jpg",
        "review": "A timeless classic exploring the struggles of adolescence.",
        "totalPages": 277,
        "rating": 4.4,
        "category": "Fiction",
        "tags": ["Coming-of-age", "Literary"],
        "publisher": "Little, Brown and Company",
        "yearOfPublishing": 1951,
        "type": "bookCard"
    },
    {
        "bookId": 4,
        "bookName": "The Great Gatsby",
        "author": "F. Scott Fitzgerald",
        "image": "https://i.postimg.cc/fRVRcwr8/The-Great-Gatsby-Cover-1925-Retouched.jpg",
        "review": "A masterpiece of modern literature capturing the decadence of the Jazz Age.",
        "totalPages": 180,
        "rating": 4.6,
        "category": "Fiction",
        "tags": ["Classics", "Romance"],
        "publisher": "Scribner",
        "yearOfPublishing": 1925,
        "type": "bookCard"
    },
    {
        "bookId": 5,
        "bookName": "The Dragon with girl",
        "author": "Stieg Larsson",
        "image": "https://i.postimg.cc/tC5xSCDy/2429135.jpg",
        "review": "A thrilling mystery with complex characters and an intricate plot.",
        "totalPages": 672,
        "rating": 4.2,
        "category": "Mystery",
        "tags": ["Suspense", "Crime"],
        "publisher": "Norstedts Förlag",
        "yearOfPublishing": 2005,
        "type": "bookCard"
    },
    {
        "bookId": 6,
        "bookName": "1984",
        "author": "George Orwell",
        "image": "https://i.postimg.cc/rsGQYXZb/njeqwu4l099141c4okfrsak1em05.jpg",
        "review": "A haunting vision of a dystopian future where freedom is restricted.",
        "totalPages": 328,
        "rating": 4.7,
        "category": "Science Fiction",
        "tags": ["Dystopian", "Political"],
        "publisher": "Secker & Warburg",
        "yearOfPublishing": 1949,
        "type": "bookCard"
    }
]
